etops/__init__.py
etops/_etops_core.cpython-39-x86_64-linux-gnu.so
etops/_version.py
etops/libeinsum_ir.so
etops.libs/libgomp-e985bcbb.so.1.0.0
etops-25.12.0.dist-info/METADATA
etops-25.12.0.dist-info/WHEEL
etops-25.12.0.dist-info/RECORD
etops-25.12.0.dist-info/licenses/LICENSE
etops-25.12.0.dist-info/sboms/auditwheel.cdx.json
