Metadata-Version: 2.4
Name: etops
Version: 25.12.0
Summary: Einsum tree operations.
Keywords: einsum trees,tensor operations
License-Expression: MIT AND BSD-3-Clause AND BSD-2-Clause
License-File: LICENSE
Project-URL: Homepage, https://github.com/scalable-analyses/einsum_ir
Project-URL: Source, https://github.com/scalable-analyses/einsum_ir
Project-URL: Issues, https://github.com/scalable-analyses/einsum_ir/issues
Requires-Python: >=3.8
Requires-Dist: numpy>=1.20
